{
    "id": "15253690055",
    "title": "Los Tuxtlas",
    "description": "Que chido!\n\n“An ant on the move does more than a dozing ox.” -Lao Tzu\n\n“The men of experiment are like the ant; they only collect and use. But the bee . . . gathers its materials from the flowers of the garden and of the field, but transforms and digests it by a power of its own.” -Leonardo da Vinci\n\n“When you have seen one ant, one bird, one tree, you have not seen them all.” -E.O. Wilson\n\n“None preaches better than the ant, and she says nothing” -Benjamin Franklin\n\n“All that is seen is my form, ant, fly, prince, and pauper” - Sri Sathya Sai Baba ",
    "tags": [
        "art",
        "pen",
        "paper",
        "ink",
        "draw",
        "drawing",
        "daniel",
        "ari",
        "friedman",
        "danielarifriedman",
        "science",
        "philosophy",
        "creative",
        "artistic",
        "geometry",
        "topology",
        "mathematics",
        "cartoon",
        "freehand",
        "freedraw",
        "craft",
        "illustration",
        "doodle",
        "sketch"
    ],
    "machine_tags": "",
    "date_taken": "2014-09-15 19:21:54",
    "owner_name": "Daniel Ari Friedman",
    "views": "565",
    "media": "photo",
    "latitude": 0,
    "longitude": 0,
    "accuracy": 0,
    "flickr_url": "https://www.flickr.com/photos/43693624@N07/15253690055",
    "available_sizes": {
        "Square": "https://live.staticflickr.com/5553/15253690055_7c9cdfb70d_s.jpg",
        "Large Square": "https://live.staticflickr.com/5553/15253690055_7c9cdfb70d_q.jpg",
        "Thumbnail": "https://live.staticflickr.com/5553/15253690055_7c9cdfb70d_t.jpg",
        "Small": "https://live.staticflickr.com/5553/15253690055_7c9cdfb70d_m.jpg",
        "Small 320": "https://live.staticflickr.com/5553/15253690055_7c9cdfb70d_n.jpg",
        "Small 400": "https://live.staticflickr.com/5553/15253690055_7c9cdfb70d_w.jpg",
        "Medium": "https://live.staticflickr.com/5553/15253690055_7c9cdfb70d.jpg",
        "Medium 640": "https://live.staticflickr.com/5553/15253690055_7c9cdfb70d_z.jpg",
        "Medium 800": "https://live.staticflickr.com/5553/15253690055_7c9cdfb70d_c.jpg",
        "Large": "https://live.staticflickr.com/5553/15253690055_7c9cdfb70d_b.jpg",
        "Large 1600": "https://live.staticflickr.com/5553/15253690055_b04a77c615_h.jpg",
        "Large 2048": "https://live.staticflickr.com/5553/15253690055_61a56ed685_k.jpg",
        "Original": "https://live.staticflickr.com/5553/15253690055_7f8eec8540_o.jpg"
    }
}