{
    "id": "22794206291",
    "title": "Action // Thought",
    "description": "“The cave you fear to enter holds the treasure you seek.”\n― Joseph Campbell\n\n“To change one’s life:\n1. Start immediately.\n2. Do it flamboyantly.\n3. No exceptions.”\n― William James\n\n&quot;This world is the great gymnasium where we come to make ourselves strong.&quot;\n― Swami Vivekananda\n\n“Your beliefs become your thoughts,\nYour thoughts become your words,\nYour words become your actions,\nYour actions become your habits,\nYour habits become your values,\nYour values become your destiny.”\n― Mahatma Gandhi \n\n\nTAGORE: There is in human affairs an element of elasticity also, some freedom within a small range which is for the expression of our personality. It is like the musical system in India, which is not so rigidly fixed as western music. Our composers give a certain definite outline, a system of melody and rhythmic arrangement, and within a certain limit the player can improvise upon it. He must be one with the law of that particular melody, and then he can give spontaneous expression to his musical feeling within the prescribed regulation. We praise the composer for his genius in creating a foundation along with a superstructure of melodies, but we expect from the player his own skill in the creation of variations of melodic flourish and ornamentation. In creation we follow the central law of existence, but if we do not cut ourselves adrift from it, we can have sufficient freedom within the limits of our personality for the fullest self-expression.\nEINSTEIN: That is possible only when there is a strong artistic tradition in music to guide the people's mind. In Europe, music has come too far away from popular art and popular feeling and has become something like a secret art with conventions and traditions of its own.\nTAGORE: You have to be absolutely obedient to this too complicated music. In India, the measure of a singer's freedom is in his own creative personality. He can sing the composer's song as his own, if he has the power creatively to assert himself in his interpretation of the general law of the melody which he is given to interpret.\nEINSTEIN: It requires a very high standard of art to realize fully the great idea in the original music, so that one can make variations upon it. In our country, the variations are often prescribed.\n\nFrom: &quot;Three conversations: Tagore Talks with Einstein, with Rolland, and Wells&quot; (Asia Magazine, March 1931).\n",
    "tags": [
        "pen",
        "paper",
        "ink",
        "drawing",
        "hand",
        "font",
        "cursive",
        "text",
        "letter",
        "english",
        "writing",
        "design",
        "language",
        "word",
        "words",
        "art",
        "draw",
        "daniel",
        "ari",
        "friedman",
        "danielarifriedman",
        "science",
        "philosophy",
        "creative",
        "artistic",
        "geometry",
        "topology",
        "mathematics",
        "cartoon",
        "freehand",
        "freedraw",
        "craft",
        "illustration",
        "doodle",
        "sketch"
    ],
    "machine_tags": "",
    "date_taken": "2015-11-04 07:27:23",
    "owner_name": "Daniel Ari Friedman",
    "views": "1788",
    "media": "photo",
    "latitude": 0,
    "longitude": 0,
    "accuracy": 0,
    "flickr_url": "https://www.flickr.com/photos/43693624@N07/22794206291",
    "available_sizes": {
        "Square": "https://live.staticflickr.com/706/22794206291_5cb7e38afd_s.jpg",
        "Large Square": "https://live.staticflickr.com/706/22794206291_5cb7e38afd_q.jpg",
        "Thumbnail": "https://live.staticflickr.com/706/22794206291_5cb7e38afd_t.jpg",
        "Small": "https://live.staticflickr.com/706/22794206291_5cb7e38afd_m.jpg",
        "Small 320": "https://live.staticflickr.com/706/22794206291_5cb7e38afd_n.jpg",
        "Small 400": "https://live.staticflickr.com/706/22794206291_5cb7e38afd_w.jpg",
        "Medium": "https://live.staticflickr.com/706/22794206291_5cb7e38afd.jpg",
        "Medium 640": "https://live.staticflickr.com/706/22794206291_5cb7e38afd_z.jpg",
        "Medium 800": "https://live.staticflickr.com/706/22794206291_5cb7e38afd_c.jpg",
        "Large": "https://live.staticflickr.com/706/22794206291_5cb7e38afd_b.jpg",
        "Large 1600": "https://live.staticflickr.com/706/22794206291_2d959e44e1_h.jpg",
        "Large 2048": "https://live.staticflickr.com/706/22794206291_3d3d6a8636_k.jpg",
        "X-Large 3K": "https://live.staticflickr.com/706/22794206291_646c1c2678_3k.jpg",
        "X-Large 4K": "https://live.staticflickr.com/706/22794206291_89e9b9c684_4k.jpg",
        "X-Large 5K": "https://live.staticflickr.com/706/22794206291_c3807e50d0_5k.jpg",
        "X-Large 6K": "https://live.staticflickr.com/706/22794206291_cc7cc2311f_6k.jpg",
        "Original": "https://live.staticflickr.com/706/22794206291_83c597d7aa_o.jpg"
    }
}