{
    "id": "25580508071",
    "title": "Connect (the Dissolution)",
    "description": "“The painter has the Universe in his mind and hands.”\n― Leonardo da Vinci\n\n“I wasn't actually in love, but I felt a sort of tender curiosity.”\n― F. Scott Fitzgerald, The Great Gatsby \n\n“You can never solve a problem on the level on which it was created.”\n― Albert Einstein\n\n“If I had my way we'd sleep every night all wrapped around each other like hibernating rattlesnakes.”\n― William S. Burroughs\n\n“A rock pile ceases to be a rock pile the moment a single man contemplates it, bearing within him the image of a cathedral.”\n― Antoine de Saint-Exupéry\n\n&quot;'And what', asks Ailsa at random, as she flicks through the pages of Darwin, 'is morphology?' \n'Morphology is dead rabbits in formalin', says Humphrey.&quot;\n― M. Drabble, The Sea Lady\n\n“The degree to which the psychiatric community is complicit with abusive parents in drugging non-compliant children is a war crime across the generations, and there will be a Nuremberg at some point in the future”\n― Stefan Molyneux\n\n“I read. I study and read. I bet I've read everything you read. Don't think I haven't. I consume libraries. I wear out spines and ROM-drives. I do things like get in a taxi and say, 'The library, and step on it.' My instincts concerning syntax and mechanics are better than your own, I can tell, with all due respect. But it transcends the mechanics. I'm not a machine. I feel and believe. I have opinions. Some of them are interesting. I could, if you'd let me, talk and talk.”\n― David Foster Wallace",
    "tags": [
        "cuddle",
        "love",
        "dyad",
        "two",
        "relationship",
        "bed",
        "sex",
        "intimate",
        "mate",
        "mating",
        "reproduction",
        "jagged",
        "velcro",
        "together",
        "touch",
        "crispr",
        "cas1",
        "cas2",
        "cas9",
        "cpf1",
        "smooth",
        "undulating",
        "sine",
        "cosine",
        "triangle",
        "tetrahedra",
        "nucleus",
        "cell",
        "membrane",
        "biology",
        "art",
        "pen",
        "paper",
        "ink",
        "draw",
        "drawing",
        "daniel",
        "ari",
        "friedman",
        "danielarifriedman",
        "science",
        "philosophy",
        "creative",
        "artistic",
        "geometry",
        "topology",
        "mathematics",
        "cartoon",
        "freehand",
        "freedraw",
        "craft",
        "illustration",
        "doodle",
        "sketch"
    ],
    "machine_tags": "",
    "date_taken": "2016-03-10 06:48:22",
    "owner_name": "Daniel Ari Friedman",
    "views": "3942",
    "media": "photo",
    "latitude": 0,
    "longitude": 0,
    "accuracy": 0,
    "flickr_url": "https://www.flickr.com/photos/43693624@N07/25580508071",
    "available_sizes": {
        "Square": "https://live.staticflickr.com/1465/25580508071_67f56300b9_s.jpg",
        "Large Square": "https://live.staticflickr.com/1465/25580508071_67f56300b9_q.jpg",
        "Thumbnail": "https://live.staticflickr.com/1465/25580508071_67f56300b9_t.jpg",
        "Small": "https://live.staticflickr.com/1465/25580508071_67f56300b9_m.jpg",
        "Small 320": "https://live.staticflickr.com/1465/25580508071_67f56300b9_n.jpg",
        "Small 400": "https://live.staticflickr.com/1465/25580508071_67f56300b9_w.jpg",
        "Medium": "https://live.staticflickr.com/1465/25580508071_67f56300b9.jpg",
        "Medium 640": "https://live.staticflickr.com/1465/25580508071_67f56300b9_z.jpg",
        "Medium 800": "https://live.staticflickr.com/1465/25580508071_67f56300b9_c.jpg",
        "Large": "https://live.staticflickr.com/1465/25580508071_67f56300b9_b.jpg",
        "Large 1600": "https://live.staticflickr.com/1465/25580508071_20f1cb550d_h.jpg",
        "Large 2048": "https://live.staticflickr.com/1465/25580508071_427e0c2d19_k.jpg",
        "X-Large 3K": "https://live.staticflickr.com/1465/25580508071_0fdd787689_3k.jpg",
        "X-Large 4K": "https://live.staticflickr.com/1465/25580508071_58ec7e7390_4k.jpg",
        "X-Large 5K": "https://live.staticflickr.com/1465/25580508071_2ffc346770_5k.jpg",
        "X-Large 6K": "https://live.staticflickr.com/1465/25580508071_988cab757b_6k.jpg",
        "Original": "https://live.staticflickr.com/1465/25580508071_2c5b3e9d6a_o.jpg"
    }
}