{
    "id": "31177485445",
    "title": "Midgut (Digestion)",
    "description": "&quot;A play is fiction - and fiction is fact distilled into truth.&quot;\n– Edward Albee\n\n&quot;Information gently but relentlessly drizzles down on us in an invisible, impalpable electric rain.&quot; \n– Hans Christian von Baeyer\n\n&quot;Nothing can sustain a system that is in overshoot. Resilience is not the strength to hold back the tide, but the strength to bend without breaking as the tide inevitably rushes in.&quot; \n– Steve Hallett\n\n&quot;The Body of\nB. Franklin, Printer,\nLike the Cover of an old Book,\nIts Contents torn out,\nAnd Stript of its Lettering &amp; Gilding,\nLies here, Food for Worms,\nBut the Work shall not be lost,\nFor, it will as he believ'd\nappear once more\nIn a new and more elegant Edition\nCorrected and improved\nBy the Author.&quot;\n– Epitaph of Benjamin Franklin",
    "tags": [
        "red",
        "white",
        "black",
        "contrast",
        "pen",
        "ink",
        "paper",
        "draw",
        "drawing",
        "art",
        "color",
        "rojo",
        "naked",
        "daniel",
        "ari",
        "friedman",
        "danielarifriedman",
        "science",
        "philosophy",
        "creative",
        "artistic",
        "geometry",
        "topology",
        "mathematics",
        "cartoon",
        "freehand",
        "freedraw",
        "craft",
        "illustration",
        "doodle",
        "sketch"
    ],
    "machine_tags": "",
    "date_taken": "2016-11-22 07:33:49",
    "owner_name": "Daniel Ari Friedman",
    "views": "2172",
    "media": "photo",
    "latitude": 0,
    "longitude": 0,
    "accuracy": 0,
    "flickr_url": "https://www.flickr.com/photos/43693624@N07/31177485445",
    "available_sizes": {
        "Square": "https://live.staticflickr.com/5707/31177485445_93478d35d0_s.jpg",
        "Large Square": "https://live.staticflickr.com/5707/31177485445_93478d35d0_q.jpg",
        "Thumbnail": "https://live.staticflickr.com/5707/31177485445_93478d35d0_t.jpg",
        "Small": "https://live.staticflickr.com/5707/31177485445_93478d35d0_m.jpg",
        "Small 320": "https://live.staticflickr.com/5707/31177485445_93478d35d0_n.jpg",
        "Small 400": "https://live.staticflickr.com/5707/31177485445_93478d35d0_w.jpg",
        "Medium": "https://live.staticflickr.com/5707/31177485445_93478d35d0.jpg",
        "Medium 640": "https://live.staticflickr.com/5707/31177485445_93478d35d0_z.jpg",
        "Medium 800": "https://live.staticflickr.com/5707/31177485445_93478d35d0_c.jpg",
        "Large": "https://live.staticflickr.com/5707/31177485445_93478d35d0_b.jpg",
        "Large 1600": "https://live.staticflickr.com/5707/31177485445_82f4fa2438_h.jpg",
        "Large 2048": "https://live.staticflickr.com/5707/31177485445_dc6813da7f_k.jpg",
        "X-Large 3K": "https://live.staticflickr.com/5707/31177485445_977511328d_3k.jpg",
        "X-Large 4K": "https://live.staticflickr.com/5707/31177485445_f0d90132d8_4k.jpg",
        "X-Large 5K": "https://live.staticflickr.com/5707/31177485445_5e3af958cd_5k.jpg",
        "X-Large 6K": "https://live.staticflickr.com/5707/31177485445_66a819edb6_6k.jpg",
        "Original": "https://live.staticflickr.com/5707/31177485445_5085ee29ea_o.jpg"
    }
}