{
    "id": "32330984124",
    "title": "The Cave",
    "description": "&quot;Understand this, I mean to arrive at the truth. The truth, however ugly in itself, is always curious and beautiful to seekers after it.&quot; \n— Agatha Christie\n\n\n&quot;Everything abstract is ultimately part of the concrete. Everything inanimate finally serves the living. That is why every activity dealing in abstraction stands in ultimate service to a living whole.&quot;\n— Edith Stein \n\n &quot;Wait a moment, here I have it. This: 'Most men will not swim before they are able to.' Is not that witty? Naturally, they won't swim! They are born for the solid earth, not for the water. And naturally they won't think. They are made for life, not for thought. Yes, and he who thinks, what's more, he who makes thought his business, he may go far in it, but he has bartered the solid earth for the water all the same, and one day he will drown.&quot; \n— Hermann Hesse, 'Steppenwolf' (1927) \n",
    "tags": [
        "black",
        "white",
        "blackandwhite",
        "bw",
        "draw",
        "drawing",
        "cartoon",
        "paper",
        "ink",
        "pen",
        "hand",
        "person",
        "self",
        "art",
        "creative",
        "artwork",
        "drawings",
        "daniel",
        "ari",
        "friedman",
        "danielarifriedman",
        "science",
        "philosophy",
        "artistic",
        "geometry",
        "topology",
        "mathematics",
        "freehand",
        "freedraw",
        "craft",
        "illustration",
        "doodle",
        "sketch"
    ],
    "machine_tags": "",
    "date_taken": "2017-02-28 13:37:28",
    "owner_name": "Daniel Ari Friedman",
    "views": "1056",
    "media": "photo",
    "latitude": 0,
    "longitude": 0,
    "accuracy": 0,
    "flickr_url": "https://www.flickr.com/photos/43693624@N07/32330984124",
    "available_sizes": {
        "Square": "https://live.staticflickr.com/3672/32330984124_e25d093474_s.jpg",
        "Large Square": "https://live.staticflickr.com/3672/32330984124_e25d093474_q.jpg",
        "Thumbnail": "https://live.staticflickr.com/3672/32330984124_e25d093474_t.jpg",
        "Small": "https://live.staticflickr.com/3672/32330984124_e25d093474_m.jpg",
        "Small 320": "https://live.staticflickr.com/3672/32330984124_e25d093474_n.jpg",
        "Small 400": "https://live.staticflickr.com/3672/32330984124_e25d093474_w.jpg",
        "Medium": "https://live.staticflickr.com/3672/32330984124_e25d093474.jpg",
        "Medium 640": "https://live.staticflickr.com/3672/32330984124_e25d093474_z.jpg",
        "Medium 800": "https://live.staticflickr.com/3672/32330984124_e25d093474_c.jpg",
        "Large": "https://live.staticflickr.com/3672/32330984124_e25d093474_b.jpg",
        "Large 1600": "https://live.staticflickr.com/3672/32330984124_f6785e9170_h.jpg",
        "Large 2048": "https://live.staticflickr.com/3672/32330984124_000f8631b8_k.jpg",
        "X-Large 3K": "https://live.staticflickr.com/3672/32330984124_f934595a0f_3k.jpg",
        "X-Large 4K": "https://live.staticflickr.com/3672/32330984124_f197794e32_4k.jpg",
        "X-Large 5K": "https://live.staticflickr.com/3672/32330984124_73acc07d4f_5k.jpg",
        "X-Large 6K": "https://live.staticflickr.com/3672/32330984124_523f26fbc6_6k.jpg",
        "Original": "https://live.staticflickr.com/3672/32330984124_274aa42f78_o.jpg"
    }
}