{
    "id": "32681300967",
    "title": "\"Fiat Fiat\" (The Agenda)",
    "description": "&quot;Though the clown is often deadpan, he is a connoisseur of laughter.&quot;\n–  Mel Gussow, about Avner Eisenberg in his broadway show Avner the Eccentric in The New York Times (21 September 1984)\n\n&quot;Young men think old men are fools; but old men know young men are fools.&quot;\n–   George Chapman, &quot;All Fools&quot; (1605), act V, scene ii, lines 205–6.\n\n&quot;FOLLY, n. That &quot;gift and faculty divine&quot; whose creative and controlling energy inspires Man's mind, guides his actions and adorns his life.&quot;\nAmbrose Bierce, The Cynic's Dictionary (1906);",
    "tags": [
        "danielarifriedman",
        "art",
        "drawing",
        "ink",
        "paper",
        "pen",
        "draw",
        "cartoon",
        "science",
        "text",
        "words",
        "letters",
        "letter",
        "font",
        "play",
        "fontplay",
        "english",
        "dollar",
        "bill",
        "satire",
        "end",
        "fed",
        "endthefed",
        "illuminati",
        "illustration",
        "doodle",
        "sketch"
    ],
    "machine_tags": "",
    "date_taken": "2019-04-16 11:33:06",
    "owner_name": "Daniel Ari Friedman",
    "views": "1619",
    "media": "photo",
    "latitude": 0,
    "longitude": 0,
    "accuracy": 0,
    "flickr_url": "https://www.flickr.com/photos/43693624@N07/32681300967",
    "available_sizes": {
        "Square": "https://live.staticflickr.com/65535/32681300967_d65a8de63b_s.jpg",
        "Large Square": "https://live.staticflickr.com/65535/32681300967_d65a8de63b_q.jpg",
        "Thumbnail": "https://live.staticflickr.com/65535/32681300967_d65a8de63b_t.jpg",
        "Small": "https://live.staticflickr.com/65535/32681300967_d65a8de63b_m.jpg",
        "Small 320": "https://live.staticflickr.com/65535/32681300967_d65a8de63b_n.jpg",
        "Small 400": "https://live.staticflickr.com/65535/32681300967_d65a8de63b_w.jpg",
        "Medium": "https://live.staticflickr.com/65535/32681300967_d65a8de63b.jpg",
        "Medium 640": "https://live.staticflickr.com/65535/32681300967_d65a8de63b_z.jpg",
        "Medium 800": "https://live.staticflickr.com/65535/32681300967_d65a8de63b_c.jpg",
        "Large": "https://live.staticflickr.com/65535/32681300967_d65a8de63b_b.jpg",
        "Large 1600": "https://live.staticflickr.com/65535/32681300967_7ef21ab384_h.jpg",
        "Large 2048": "https://live.staticflickr.com/65535/32681300967_da190a0af2_k.jpg",
        "X-Large 3K": "https://live.staticflickr.com/65535/32681300967_36169219b2_3k.jpg",
        "X-Large 4K": "https://live.staticflickr.com/65535/32681300967_37d14a2d53_4k.jpg",
        "X-Large 5K": "https://live.staticflickr.com/65535/32681300967_006ae7d576_5k.jpg",
        "X-Large 6K": "https://live.staticflickr.com/65535/32681300967_d25b630e3f_6k.jpg",
        "Original": "https://live.staticflickr.com/65535/32681300967_2af2d0893d_o.jpg"
    }
}