{
    "id": "33035191686",
    "title": "Theory: Hypothesis & Experiment",
    "description": "&quot;When Adam first of men,\nTo first of women Eve, thus moving speech,\nTurn'd him all ear to hear new utterance flow.&quot;\n​— John Milton, 'Paradise Lost' \n\n&quot;Eventually it may be possible for humans to speak with another species. I have come to this conclusion after careful consideration of evidence gained through my research experiments with dolphins. If new scientific developments are to be made in this direction, however, certain changes in our basic orientation and philosophy will be necessary.&quot;\n​— John Lily, 'Man and Dolphin' (1961).\n\n&quot;The restriction of rationality to the use of means … entails that the other aspect of the practical problematic, the realm of ends, falls prey to pure decisionism, the whim of mere decisions not reflected upon by reason. The decisionism of unreflected, arbitrary decisions in the realm of practice corresponds to the positivism implied by the restriction to pure value-free theories.&quot;\n​— Hans Albert, 'The Myth of Total Reason​' (1969). ​​​​\n\n\n",
    "tags": [
        "art",
        "pen",
        "paper",
        "ink",
        "draw",
        "drawing",
        "daniel",
        "ari",
        "friedman",
        "danielarifriedman",
        "science",
        "philosophy",
        "creative",
        "artistic",
        "geometry",
        "topology",
        "mathematics",
        "cartoon",
        "freehand",
        "freedraw",
        "craft",
        "illustration",
        "doodle",
        "sketch"
    ],
    "machine_tags": "",
    "date_taken": "2017-02-23 12:50:46",
    "owner_name": "Daniel Ari Friedman",
    "views": "935",
    "media": "photo",
    "latitude": 0,
    "longitude": 0,
    "accuracy": 0,
    "flickr_url": "https://www.flickr.com/photos/43693624@N07/33035191686",
    "available_sizes": {
        "Square": "https://live.staticflickr.com/2172/33035191686_a56bfafb32_s.jpg",
        "Large Square": "https://live.staticflickr.com/2172/33035191686_a56bfafb32_q.jpg",
        "Thumbnail": "https://live.staticflickr.com/2172/33035191686_a56bfafb32_t.jpg",
        "Small": "https://live.staticflickr.com/2172/33035191686_a56bfafb32_m.jpg",
        "Small 320": "https://live.staticflickr.com/2172/33035191686_a56bfafb32_n.jpg",
        "Small 400": "https://live.staticflickr.com/2172/33035191686_a56bfafb32_w.jpg",
        "Medium": "https://live.staticflickr.com/2172/33035191686_a56bfafb32.jpg",
        "Medium 640": "https://live.staticflickr.com/2172/33035191686_a56bfafb32_z.jpg",
        "Medium 800": "https://live.staticflickr.com/2172/33035191686_a56bfafb32_c.jpg",
        "Large": "https://live.staticflickr.com/2172/33035191686_a56bfafb32_b.jpg",
        "Large 1600": "https://live.staticflickr.com/2172/33035191686_fbf1c66101_h.jpg",
        "Large 2048": "https://live.staticflickr.com/2172/33035191686_e816168df6_k.jpg",
        "X-Large 3K": "https://live.staticflickr.com/2172/33035191686_405a75eb51_3k.jpg",
        "X-Large 4K": "https://live.staticflickr.com/2172/33035191686_437fadfe77_4k.jpg",
        "X-Large 5K": "https://live.staticflickr.com/2172/33035191686_de727e60d2_5k.jpg",
        "X-Large 6K": "https://live.staticflickr.com/2172/33035191686_b9eaaa21aa_6k.jpg",
        "Original": "https://live.staticflickr.com/2172/33035191686_5db077a3d2_o.jpg"
    }
}