{
    "id": "34608362900",
    "title": "Paper Is A Natural Artefact",
    "description": "paper is a natural artefact, like hair, teeth, nails, or bone, and should be treated as such.\n\n~~~~~~~~~~~~~~\n\n&quot;The house is a castle which the King cannot enter.&quot;\n– Ralph Waldo Emerson\n\n&quot;There are two kinds of fools: one says, 'This is old, therefore it is good'; the other says, 'This is new, therefore it is better.'&quot;\n– Dean Inge\n\n&quot;Such is the advantage of a well-constructed language that its simplified notation often becomes the source of profound theories.&quot;\n– Pierre Simon Marquis de Laplace \n\n&quot;Free from desire, you realize the mystery.\nCaught in desire, you see only the manifestations.\nYet mystery and manifestations\narise from the same source.\nThis source is called darkness.\nDarkness within darkness.\nThe gateway to all understanding.&quot;\n– Laozi, 'Tao Te Ching', Ch.1",
    "tags": [
        "pen",
        "paper",
        "ink",
        "art",
        "drawing",
        "draw",
        "hand",
        "person",
        "mind",
        "self",
        "daniel",
        "ari",
        "friedman",
        "danielarifriedman",
        "science",
        "philosophy",
        "creative",
        "artistic",
        "geometry",
        "topology",
        "mathematics",
        "cartoon",
        "freehand",
        "freedraw",
        "craft",
        "illustration",
        "doodle",
        "sketch"
    ],
    "machine_tags": "",
    "date_taken": "2017-05-30 12:01:38",
    "owner_name": "Daniel Ari Friedman",
    "views": "1005",
    "media": "photo",
    "latitude": 0,
    "longitude": 0,
    "accuracy": 0,
    "flickr_url": "https://www.flickr.com/photos/43693624@N07/34608362900",
    "available_sizes": {
        "Square": "https://live.staticflickr.com/4276/34608362900_dcb1aeddf3_s.jpg",
        "Large Square": "https://live.staticflickr.com/4276/34608362900_dcb1aeddf3_q.jpg",
        "Thumbnail": "https://live.staticflickr.com/4276/34608362900_dcb1aeddf3_t.jpg",
        "Small": "https://live.staticflickr.com/4276/34608362900_dcb1aeddf3_m.jpg",
        "Small 320": "https://live.staticflickr.com/4276/34608362900_dcb1aeddf3_n.jpg",
        "Small 400": "https://live.staticflickr.com/4276/34608362900_dcb1aeddf3_w.jpg",
        "Medium": "https://live.staticflickr.com/4276/34608362900_dcb1aeddf3.jpg",
        "Medium 640": "https://live.staticflickr.com/4276/34608362900_dcb1aeddf3_z.jpg",
        "Medium 800": "https://live.staticflickr.com/4276/34608362900_dcb1aeddf3_c.jpg",
        "Large": "https://live.staticflickr.com/4276/34608362900_dcb1aeddf3_b.jpg",
        "Large 1600": "https://live.staticflickr.com/4276/34608362900_0368e29db7_h.jpg",
        "Large 2048": "https://live.staticflickr.com/4276/34608362900_d4b389b6b9_k.jpg",
        "X-Large 3K": "https://live.staticflickr.com/4276/34608362900_f8a93fb734_3k.jpg",
        "X-Large 4K": "https://live.staticflickr.com/4276/34608362900_55f6e9c193_4k.jpg",
        "X-Large 5K": "https://live.staticflickr.com/4276/34608362900_5211561e00_5k.jpg",
        "X-Large 6K": "https://live.staticflickr.com/4276/34608362900_d3874f88da_6k.jpg",
        "Original": "https://live.staticflickr.com/4276/34608362900_61a100dcc1_o.jpg"
    }
}