{
    "id": "39220290864",
    "title": "Wormhole",
    "description": "&quot;You are not like Cerberus, three gentlemen at once, are you?&quot;\n– Richard Brinsley Sheridan, The Rivals (1775)\n\n&quot;But when ﬁrst the two black dragons sprang out of the fog upon the small clerk, they had merely the eﬀect of all miracles – they changed the universe. He discovered the fact that all romantics know – that adventures happen on dull days, and not on sunny ones. When the cord of monotony is stretched most tight, it it breaks with a sound like song.&quot;\n– G. K. Chesterton, 'The Napoleon of Notting Hill' (1904).\n\n&quot;The collapse of the global marketplace would be a traumatic event with unimaginable consequences. Yet I find it easier to imagine than the continuation of the present regime.&quot; [sic!].\n– George Soros, in 'Soros on Soros : Staying Ahead of the Curve' (1995 [??])",
    "tags": [
        "black",
        "white",
        "blackwhite",
        "bw",
        "drawing",
        "draw",
        "pen",
        "ink",
        "paper",
        "watercolor",
        "creative",
        "art",
        "daniel",
        "friedman",
        "danielarifriedman",
        "science",
        "philosophy",
        "artistic",
        "geometry",
        "topology",
        "mathematics",
        "cartoon",
        "freehand",
        "freedraw",
        "craft",
        "illustration",
        "doodle",
        "sketch"
    ],
    "machine_tags": "",
    "date_taken": "2018-01-27 10:30:30",
    "owner_name": "Daniel Ari Friedman",
    "views": "4292",
    "media": "photo",
    "latitude": 0,
    "longitude": 0,
    "accuracy": 0,
    "flickr_url": "https://www.flickr.com/photos/43693624@N07/39220290864",
    "available_sizes": {
        "Square": "https://live.staticflickr.com/4769/39220290864_aee30c8e7c_s.jpg",
        "Large Square": "https://live.staticflickr.com/4769/39220290864_aee30c8e7c_q.jpg",
        "Thumbnail": "https://live.staticflickr.com/4769/39220290864_aee30c8e7c_t.jpg",
        "Small": "https://live.staticflickr.com/4769/39220290864_aee30c8e7c_m.jpg",
        "Small 320": "https://live.staticflickr.com/4769/39220290864_aee30c8e7c_n.jpg",
        "Small 400": "https://live.staticflickr.com/4769/39220290864_aee30c8e7c_w.jpg",
        "Medium": "https://live.staticflickr.com/4769/39220290864_aee30c8e7c.jpg",
        "Medium 640": "https://live.staticflickr.com/4769/39220290864_aee30c8e7c_z.jpg",
        "Medium 800": "https://live.staticflickr.com/4769/39220290864_aee30c8e7c_c.jpg",
        "Large": "https://live.staticflickr.com/4769/39220290864_aee30c8e7c_b.jpg",
        "Large 1600": "https://live.staticflickr.com/4769/39220290864_9d2fe628c6_h.jpg",
        "Large 2048": "https://live.staticflickr.com/4769/39220290864_3b7cd1d945_k.jpg",
        "X-Large 3K": "https://live.staticflickr.com/4769/39220290864_40616ee53b_3k.jpg",
        "X-Large 4K": "https://live.staticflickr.com/4769/39220290864_ce51328614_4k.jpg",
        "X-Large 5K": "https://live.staticflickr.com/4769/39220290864_096e783580_5k.jpg",
        "X-Large 6K": "https://live.staticflickr.com/4769/39220290864_d613159063_6k.jpg",
        "Original": "https://live.staticflickr.com/4769/39220290864_45c6733aaf_o.jpg"
    }
}