{
    "id": "42675028622",
    "title": "Evolution of Sociality",
    "description": "&quot;The Arch-flatterer, with whom all the petty flatterers have intelligence, is a man’s self.&quot;\n– Francis Bacon. ‘On Love’, Essays (1597-1625)\n\n&quot;As far as we can discern, the sole purpose of human existence is to kindle a light in the darkness of mere being.&quot;\n– Carl Jung\n\n&quot;General Systems Theory, as originally intended by Von Bertalanffy, is an ideal framework for the modeling of a business enterprise. Work, in its most civilized form should enrich, empower and emancipate. Thus we must continue to find ways to support work as a humanistic, not mechanistic endeavor. We must continue to seek out new models of business that support and enhance the individual as well as the collective whole. Given all this new technology, we need new institutions for handling it.&quot;\n– Anthony Stafford Beer (1974), &quot;Designing Freedom&quot;.",
    "tags": [
        "pen",
        "paper",
        "ink",
        "draw",
        "drawing",
        "danielarifriedman",
        "daniel",
        "friedman",
        "art",
        "science",
        "philosophy",
        "red",
        "green",
        "color",
        "person",
        "creative",
        "cartoon",
        "picture",
        "image",
        "artistic",
        "geometry",
        "topology",
        "mathematics",
        "freehand",
        "freedraw",
        "craft",
        "illustration",
        "doodle",
        "sketch"
    ],
    "machine_tags": "",
    "date_taken": "2018-06-10 18:12:35",
    "owner_name": "Daniel Ari Friedman",
    "views": "1099",
    "media": "photo",
    "latitude": 0,
    "longitude": 0,
    "accuracy": 0,
    "flickr_url": "https://www.flickr.com/photos/43693624@N07/42675028622",
    "available_sizes": {
        "Square": "https://live.staticflickr.com/1732/42675028622_5a96b7e9e9_s.jpg",
        "Large Square": "https://live.staticflickr.com/1732/42675028622_5a96b7e9e9_q.jpg",
        "Thumbnail": "https://live.staticflickr.com/1732/42675028622_5a96b7e9e9_t.jpg",
        "Small": "https://live.staticflickr.com/1732/42675028622_5a96b7e9e9_m.jpg",
        "Small 320": "https://live.staticflickr.com/1732/42675028622_5a96b7e9e9_n.jpg",
        "Small 400": "https://live.staticflickr.com/1732/42675028622_5a96b7e9e9_w.jpg",
        "Medium": "https://live.staticflickr.com/1732/42675028622_5a96b7e9e9.jpg",
        "Medium 640": "https://live.staticflickr.com/1732/42675028622_5a96b7e9e9_z.jpg",
        "Medium 800": "https://live.staticflickr.com/1732/42675028622_5a96b7e9e9_c.jpg",
        "Large": "https://live.staticflickr.com/1732/42675028622_5a96b7e9e9_b.jpg",
        "Large 1600": "https://live.staticflickr.com/1732/42675028622_746c62d63d_h.jpg",
        "Large 2048": "https://live.staticflickr.com/1732/42675028622_83d6e4c0a4_k.jpg",
        "X-Large 3K": "https://live.staticflickr.com/1732/42675028622_bdd1f1d08f_3k.jpg",
        "X-Large 4K": "https://live.staticflickr.com/1732/42675028622_835065a222_4k.jpg",
        "X-Large 5K": "https://live.staticflickr.com/1732/42675028622_88e300a94f_5k.jpg",
        "X-Large 6K": "https://live.staticflickr.com/1732/42675028622_0725b8626c_6k.jpg",
        "Original": "https://live.staticflickr.com/1732/42675028622_78f2cedff7_o.jpg"
    }
}