{
    "id": "43920162014",
    "title": "Ant Head",
    "description": "&quot;Ita fabulantur ut qui sciant Dominum audire.&quot;\n[They converse as those who know that God hears.]\n– Tertullian (ca. 150-220) , &quot;Apologeticus&quot;, p. 36.\n\n&quot;To make the right decision the knowledge-worker must know what performance and results are needed... He cannot be supervised. He must direct, manage and motivate himself.&quot;\n– Peter Drucker (1964), &quot;Managing For Results&quot;, Harper &amp; Row, New York, p. 222.\n\n&quot;Culture is at once the expression and the reward of an effort, and any system of civilization which tends to relax effort will suffer a corresponding depreciation of culture.&quot;\n– Georges Duhamel, &quot;In Defense of Letters&quot; (1937).",
    "tags": [
        "drawing",
        "draw",
        "art",
        "science",
        "philosophy",
        "paper",
        "pen",
        "ink",
        "creative",
        "artistic",
        "geometry",
        "topology",
        "mathematics",
        "cartoon",
        "freehand",
        "freedraw",
        "craft",
        "illustration",
        "doodle",
        "sketch"
    ],
    "machine_tags": "",
    "date_taken": "2018-09-12 09:11:24",
    "owner_name": "Daniel Ari Friedman",
    "views": "1167",
    "media": "photo",
    "latitude": 0,
    "longitude": 0,
    "accuracy": 0,
    "flickr_url": "https://www.flickr.com/photos/43693624@N07/43920162014",
    "available_sizes": {
        "Square": "https://live.staticflickr.com/1870/43920162014_85454f72f2_s.jpg",
        "Large Square": "https://live.staticflickr.com/1870/43920162014_85454f72f2_q.jpg",
        "Thumbnail": "https://live.staticflickr.com/1870/43920162014_85454f72f2_t.jpg",
        "Small": "https://live.staticflickr.com/1870/43920162014_85454f72f2_m.jpg",
        "Small 320": "https://live.staticflickr.com/1870/43920162014_85454f72f2_n.jpg",
        "Small 400": "https://live.staticflickr.com/1870/43920162014_85454f72f2_w.jpg",
        "Medium": "https://live.staticflickr.com/1870/43920162014_85454f72f2.jpg",
        "Medium 640": "https://live.staticflickr.com/1870/43920162014_85454f72f2_z.jpg",
        "Medium 800": "https://live.staticflickr.com/1870/43920162014_85454f72f2_c.jpg",
        "Large": "https://live.staticflickr.com/1870/43920162014_85454f72f2_b.jpg",
        "Large 1600": "https://live.staticflickr.com/1870/43920162014_0f7ecc6067_h.jpg",
        "Large 2048": "https://live.staticflickr.com/1870/43920162014_e54d8ef8d4_k.jpg",
        "X-Large 3K": "https://live.staticflickr.com/1870/43920162014_69f4740873_3k.jpg",
        "X-Large 4K": "https://live.staticflickr.com/1870/43920162014_ded5913257_4k.jpg",
        "X-Large 5K": "https://live.staticflickr.com/1870/43920162014_32c13db0ae_5k.jpg",
        "Original": "https://live.staticflickr.com/1870/43920162014_470b592642_o.jpg"
    }
}