{
    "id": "46008897444",
    "title": "State \"Education\"",
    "description": "&quot;Saint Valentine is past;\nBegin these wood-birds but to couple now?&quot;\n– William Shakespeare, &quot;A Midsummer Night's Dream&quot; (c. 1595-96), Act IV, scene 1, line 144.\n\n&quot;For this was on seynt Volantynys day\nWhan euery bryd comyth there to chese his make.&quot;\nTranslation:\n&quot;For this was Saint Valentine's Day,\nWhen every bird cometh there to choose his mate.&quot;\n– Geoffrey Chaucer, &quot;Parlement of Foules&quot; (1382 [!]).\n\n&quot;The stronger the thunder, the more powerful the lightning. All reiterate—the New Age arrives in storm and lightning. For the lightning there are needed positive and negative energies. If Maya does not furnish the negative evidence, how then can flash forth the sword-blade of positive reality?&quot;\n– Agni Yoga, &quot;New Era Community&quot; (1926).",
    "tags": [
        "danielarifriedman",
        "daniel",
        "friedman",
        "art",
        "drawing",
        "paper",
        "ink",
        "freehand",
        "draw",
        "2019",
        "january",
        "gold",
        "golden",
        "goldy",
        "faith",
        "home",
        "school",
        "homeschool",
        "politics",
        "group",
        "groupthink",
        "think",
        "thought",
        "conspiracy",
        "theory",
        "science",
        "belief",
        "state",
        "nation",
        "education",
        "propaganda",
        "philosophy",
        "pen",
        "creative",
        "artistic",
        "geometry",
        "topology",
        "mathematics",
        "cartoon",
        "freedraw",
        "craft",
        "illustration",
        "doodle",
        "sketch"
    ],
    "machine_tags": "",
    "date_taken": "2019-01-13 17:31:44",
    "owner_name": "Daniel Ari Friedman",
    "views": "1883",
    "media": "photo",
    "latitude": 0,
    "longitude": 0,
    "accuracy": 0,
    "flickr_url": "https://www.flickr.com/photos/43693624@N07/46008897444",
    "available_sizes": {
        "Square": "https://live.staticflickr.com/4863/46008897444_6b876068f7_s.jpg",
        "Large Square": "https://live.staticflickr.com/4863/46008897444_6b876068f7_q.jpg",
        "Thumbnail": "https://live.staticflickr.com/4863/46008897444_6b876068f7_t.jpg",
        "Small": "https://live.staticflickr.com/4863/46008897444_6b876068f7_m.jpg",
        "Small 320": "https://live.staticflickr.com/4863/46008897444_6b876068f7_n.jpg",
        "Small 400": "https://live.staticflickr.com/4863/46008897444_6b876068f7_w.jpg",
        "Medium": "https://live.staticflickr.com/4863/46008897444_6b876068f7.jpg",
        "Medium 640": "https://live.staticflickr.com/4863/46008897444_6b876068f7_z.jpg",
        "Medium 800": "https://live.staticflickr.com/4863/46008897444_6b876068f7_c.jpg",
        "Large": "https://live.staticflickr.com/4863/46008897444_6b876068f7_b.jpg",
        "Large 1600": "https://live.staticflickr.com/4863/46008897444_be98fecc54_h.jpg",
        "Large 2048": "https://live.staticflickr.com/4863/46008897444_fdfd62a735_k.jpg",
        "X-Large 3K": "https://live.staticflickr.com/4863/46008897444_7d7ac1a6c1_3k.jpg",
        "X-Large 4K": "https://live.staticflickr.com/4863/46008897444_56020dc201_4k.jpg",
        "X-Large 5K": "https://live.staticflickr.com/4863/46008897444_c0afd4b9c7_5k.jpg",
        "X-Large 6K": "https://live.staticflickr.com/4863/46008897444_896830da64_6k.jpg",
        "Original": "https://live.staticflickr.com/4863/46008897444_46deb25bc1_o.jpg"
    }
}