{
    "id": "48044479243",
    "title": "Life is a Pyramid Scheme for Information",
    "description": "&quot;The academies and universities satisfied Socrates’ demand to be fed in the prytaneum.&quot;\n– Allan Bloom, “Commerce and Culture,” Giants and Dwarfs (1990), p. 289.\n\n&quot;Some misguided men learn the Dhamma ... only for the sake of criticising others and for winning in debates, and they do not experience the good for the sake of which they learned the Dhamma.&quot;\n– Gautama Buddha, Majjhima Nikaya, Alagaddūpama Sutta, Sutta 22, verse 10, p. 227\n\nACADEME, n. An ancient school where morality and philosophy were taught.\nACADEMY, n. [from ACADEME] A modern school where football is taught.\n– Ambrose Bierce, &quot;The Cynic's Dictionary&quot; (1906); republished as &quot;The Devil's Dictionary&quot; (1911).",
    "tags": [
        "black",
        "drawing",
        "art",
        "daniel",
        "friedman",
        "ari",
        "danielarifriedman",
        "hand",
        "pen",
        "ink",
        "draw",
        "texture",
        "cartoon",
        "sketch",
        "doodle",
        "red",
        "color",
        "gold",
        "text",
        "writing",
        "letters"
    ],
    "machine_tags": "",
    "date_taken": "2019-06-11 09:54:04",
    "owner_name": "Daniel Ari Friedman",
    "views": "1319",
    "media": "photo",
    "latitude": 0,
    "longitude": 0,
    "accuracy": 0,
    "flickr_url": "https://www.flickr.com/photos/43693624@N07/48044479243",
    "available_sizes": {
        "Square": "https://live.staticflickr.com/65535/48044479243_9fdb6179ea_s.jpg",
        "Large Square": "https://live.staticflickr.com/65535/48044479243_9fdb6179ea_q.jpg",
        "Thumbnail": "https://live.staticflickr.com/65535/48044479243_9fdb6179ea_t.jpg",
        "Small": "https://live.staticflickr.com/65535/48044479243_9fdb6179ea_m.jpg",
        "Small 320": "https://live.staticflickr.com/65535/48044479243_9fdb6179ea_n.jpg",
        "Small 400": "https://live.staticflickr.com/65535/48044479243_9fdb6179ea_w.jpg",
        "Medium": "https://live.staticflickr.com/65535/48044479243_9fdb6179ea.jpg",
        "Medium 640": "https://live.staticflickr.com/65535/48044479243_9fdb6179ea_z.jpg",
        "Medium 800": "https://live.staticflickr.com/65535/48044479243_9fdb6179ea_c.jpg",
        "Large": "https://live.staticflickr.com/65535/48044479243_9fdb6179ea_b.jpg",
        "Large 1600": "https://live.staticflickr.com/65535/48044479243_29efc9abb6_h.jpg",
        "Large 2048": "https://live.staticflickr.com/65535/48044479243_bee982f41c_k.jpg",
        "X-Large 3K": "https://live.staticflickr.com/65535/48044479243_15e3fdce8f_3k.jpg",
        "X-Large 4K": "https://live.staticflickr.com/65535/48044479243_516c827df9_4k.jpg",
        "X-Large 5K": "https://live.staticflickr.com/65535/48044479243_86b404e7f3_5k.jpg",
        "X-Large 6K": "https://live.staticflickr.com/65535/48044479243_15137ef465_6k.jpg",
        "Original": "https://live.staticflickr.com/65535/48044479243_80884ec21c_o.jpg"
    }
}