{
    "id": "49831318917",
    "title": "LIBERTAS ET PATRIA",
    "description": "&quot;We are testing popular government's capacity for self-defense. We are resolved to liberate the soul of American life and prove ourselves an American people in fact, spirit, and purpose, and consecrate ourselves anew and everlastingly to human freedom and humanity's justice. Realizing our new relationship with the world, we want to make it fit to live in, and with might and fright and wrathfulness and barbarity crushed by the conscience of a real civilization. Ours is a small concern about the kind of government any people may choose, but we do mean to outlaw the nation which violates the sacred compacts of international relationships. The decision is to be final... A republic worth living in is worth fighting for, and sacrificing for, and dying for. In the fires of this conflict we shall wipe out the disloyalty of those who wear American garb without the faith, and establish a new concord of citizenship and a new devotion, so that we should have made a safe America the home and hope of a people who are truly American in heart and soul.&quot;–  Warren G. Harding, The Republic Must Awaken (1917).\n\n&quot;Much has been said of late about world ideals, but I prefer to think of the ideal for America. I like to think there's something more than the patriotism and practical wisdom of the founding fathers. It's good to believe that maybe destiny held this new world republic to be the supreme example of representative democracy and orderly liberty by which humanity is inspired to higher achievement. It is idle to think we have attained perfection, but there is the satisfying knowledge that we hold orderly processes for making our government reflect the heart and mind of the republic... Ours is not only a fortunate people, but a very common-sensical people, with vision high, but their feet on the earth, with belief in themselves and faith in God. Whether enemies threaten from without or menaces arise from within, there is some indefinable voice saying, ‍'‍Have confidence in the Republic. America will go on‍'‍. Here is the sample of liberty no storms may shake. Here are the altars of freedom no factions shall destroy. It was American in conception, American in its building. It shall be American in the fulfillment. Factional once, we are all American now, and we mean to be all Americans to all the world.&quot;\n–   Warren G. Harding, The American Soldier (1920).\n\n\n&quot;[M]ankind are all formed by the same Almighty being, alike objects of his Care &amp; equally designed for the Enjoyment of Happiness the Christian Religion teaches us to believe &amp; the Political Creed of America fully coincides with the Position... [B]lessings ought rightfully to be administered, without distinction of Colour, to all descriptions of People, so they indulge themselves in the pleasing expectation, that nothing, which can be done for the relive of the unhappy objects of their care, will be either omitted or delayed... From a persuasion that equal liberty was originally the Portion, It is still the Birthright of all men.&quot;\n–   Benjamin Franklin, &quot;Petition from the Pennsylvania Society for the Abolition of Slavery&quot; (3 February 1790)\n",
    "tags": [
        "black",
        "pen",
        "ink",
        "writing",
        "paper",
        "creative",
        "draw",
        "usa",
        "america",
        "donald",
        "trump",
        "united",
        "country",
        "nation",
        "states",
        "nationalism",
        "drawing",
        "cartoon",
        "art",
        "sketch",
        "patriotic",
        "abstract",
        "texture",
        "modern"
    ],
    "machine_tags": "",
    "date_taken": "2020-01-01 12:00:00",
    "owner_name": "Daniel Ari Friedman",
    "views": "1833",
    "media": "photo",
    "latitude": 0,
    "longitude": 0,
    "accuracy": 0,
    "flickr_url": "https://www.flickr.com/photos/43693624@N07/49831318917",
    "available_sizes": {
        "Square": "https://live.staticflickr.com/65535/49831318917_eca3ce53be_s.jpg",
        "Large Square": "https://live.staticflickr.com/65535/49831318917_eca3ce53be_q.jpg",
        "Thumbnail": "https://live.staticflickr.com/65535/49831318917_eca3ce53be_t.jpg",
        "Small": "https://live.staticflickr.com/65535/49831318917_eca3ce53be_m.jpg",
        "Small 320": "https://live.staticflickr.com/65535/49831318917_eca3ce53be_n.jpg",
        "Small 400": "https://live.staticflickr.com/65535/49831318917_eca3ce53be_w.jpg",
        "Medium": "https://live.staticflickr.com/65535/49831318917_eca3ce53be.jpg",
        "Medium 640": "https://live.staticflickr.com/65535/49831318917_eca3ce53be_z.jpg",
        "Medium 800": "https://live.staticflickr.com/65535/49831318917_eca3ce53be_c.jpg",
        "Large": "https://live.staticflickr.com/65535/49831318917_eca3ce53be_b.jpg",
        "Large 1600": "https://live.staticflickr.com/65535/49831318917_52c564425d_h.jpg",
        "Large 2048": "https://live.staticflickr.com/65535/49831318917_9e012c9fa9_k.jpg",
        "X-Large 3K": "https://live.staticflickr.com/65535/49831318917_59fb42b75b_3k.jpg",
        "X-Large 4K": "https://live.staticflickr.com/65535/49831318917_9581e03fcd_4k.jpg",
        "X-Large 5K": "https://live.staticflickr.com/65535/49831318917_22f561ca2c_5k.jpg",
        "X-Large 6K": "https://live.staticflickr.com/65535/49831318917_9add4060c8_6k.jpg",
        "Original": "https://live.staticflickr.com/65535/49831318917_ba54d04be9_o.jpg"
    }
}